exli/__init__.py
exli/__main__.py
exli/_cmd_utils.py
exli/_const.py
exli/main.py
exli-0.1.1.dist-info/LICENSE
exli-0.1.1.dist-info/METADATA
exli-0.1.1.dist-info/WHEEL
exli-0.1.1.dist-info/entry_points.txt
exli-0.1.1.dist-info/top_level.txt
exli-0.1.1.dist-info/RECORD
