Metadata-Version: 2.1
Name: exli
Version: 0.1.1
Summary: An alias manager and an infinitely extensible CLI.
Home-page: https://github.com/Adwaith-Rajesh/exli
Author: Adwaith-Rajesh
Author-email: adwaithajesh3180@gmail.com
License: MIT
Platform: UNKNOWN
Classifier: Intended Audience :: Developers
Classifier: License :: OSI Approved :: MIT License
Classifier: Operating System :: POSIX
Classifier: Programming Language :: Python :: 3
Classifier: Programming Language :: Python :: 3 :: Only
Classifier: Programming Language :: Python :: 3.6
Classifier: Programming Language :: Python :: 3.7
Classifier: Programming Language :: Python :: 3.8
Classifier: Programming Language :: Python :: 3.9
Requires-Python: >=3.6.1
License-File: LICENSE
